
{"order":100,"items":[{"name":"Create Baseline","href":"create-baseline.html","topicHref":"create-baseline.html"},{"name":"View Baselines","href":"query-baselines.html","topicHref":"query-baselines.html"},{"name":"View Job Report","href":"query-create-baseline-job-report-detail.html","topicHref":"query-create-baseline-job-report-detail.html"},{"name":"View Job Details","href":"query-job.html","topicHref":"query-job.html"},{"name":"View Tenant","href":"query-tenant.html","topicHref":"query-tenant.html"},{"name":"View Tenant Actions","href":"tenant-action.html","topicHref":"tenant-action.html"}],"pdf":false,"pdfFileName":"AvePoint Graph API Documentation.pdf","pdfTocPage":true}
