{
  "x-generator": "NSwag v14.2.0.0 (NJsonSchema v11.1.0.0 (Newtonsoft.Json v13.0.0.0))",
  "openapi": "3.0.0",
  "info": {
    "title": "Cloud Backup for Office 365 Web Api 2",
    "description": "This is Cloud Backup for Office 365 Web Api",
    "contact": {
      "name": "AvePoint Cloud Backup for Office 365",
      "url": "https://avepointcdn.azureedge.net/assets/webhelp/avepoint-cloud-backup-for-office365/index.htm",
      "email": "ACB@avepoint.com"
    },
    "license": {
      "name": "ACB License",
      "url": "https://test.sharepointguild.com/"
    },
    "version": "1.0.0"
  },
  "servers": [
    {
      "url": "https://10.2.156.34:12580"
    }
  ],
  "paths": {
    "/cloudbackup/licenseconsumption": {
      "get": {
        "tags": [
          "PublicApi"
        ],
        "operationId": "PublicApi_GetCloudBackupLicenseConsumption",
        "responses": {
          "200": {
            "description": "",
            "content": {
              "application/json": {
                "schema": {
                  "$ref": "#/components/schemas/LicenseConsumption"
                }
              }
            }
          }
        }
      }
    },
    "/cloudbackup/getjobs": {
      "get": {
        "tags": [
          "PublicApi"
        ],
        "operationId": "PublicApi_GetJobs",
        "parameters": [
          {
            "name": "StartTime",
            "in": "query",
            "schema": {
              "type": "string",
              "nullable": true
            },
            "x-position": 1
          },
          {
            "name": "FinishTime",
            "in": "query",
            "schema": {
              "type": "string",
              "nullable": true
            },
            "x-position": 2
          },
          {
            "name": "JobType",
            "in": "query",
            "schema": {
              "$ref": "#/components/schemas/BackupJobType"
            },
            "x-position": 3
          },
          {
            "name": "ObjectType",
            "in": "query",
            "schema": {
              "$ref": "#/components/schemas/CloudBackupJobObjectType"
            },
            "x-position": 4
          },
          {
            "name": "JobState",
            "in": "query",
            "schema": {
              "$ref": "#/components/schemas/CloudBackupJobState"
            },
            "x-position": 5
          },
          {
            "name": "PageIndex",
            "in": "query",
            "schema": {
              "type": "integer",
              "format": "int32"
            },
            "x-position": 6
          },
          {
            "name": "PageSize",
            "in": "query",
            "schema": {
              "type": "integer",
              "format": "int32"
            },
            "x-position": 7
          }
        ],
        "responses": {
          "200": {
            "description": "",
            "content": {
              "application/json": {
                "schema": {
                  "$ref": "#/components/schemas/PublicApiGetJobResult"
                }
              }
            }
          }
        }
      }
    },
    "/cloudbackup/getunusualactivitydata": {
      "get": {
        "tags": [
          "PublicApi"
        ],
        "operationId": "PublicApi_GetUnusualActivityData",
        "parameters": [
          {
            "name": "StartTime",
            "in": "query",
            "schema": {
              "type": "string",
              "nullable": true
            },
            "x-position": 1
          },
          {
            "name": "EndTime",
            "in": "query",
            "schema": {
              "type": "string",
              "nullable": true
            },
            "x-position": 2
          }
        ],
        "responses": {
          "200": {
            "description": "",
            "content": {
              "application/json": {
                "schema": {
                  "$ref": "#/components/schemas/PublicApiGetUnusualActivity"
                }
              }
            }
          }
        }
      }
    },
    "/cloudbackup/jobs": {
      "get": {
        "tags": [
          "PublicApi"
        ],
        "operationId": "PublicApi_GetCloudBackupJobs",
        "parameters": [
          {
            "name": "StartTime",
            "in": "query",
            "schema": {
              "type": "integer",
              "format": "int64"
            },
            "x-position": 1
          },
          {
            "name": "FinishTime",
            "in": "query",
            "schema": {
              "type": "integer",
              "format": "int64"
            },
            "x-position": 2
          },
          {
            "name": "JobType",
            "in": "query",
            "schema": {
              "$ref": "#/components/schemas/BackupJobType"
            },
            "x-position": 3
          },
          {
            "name": "ObjectType",
            "in": "query",
            "schema": {
              "$ref": "#/components/schemas/CloudBackupJobObjectType"
            },
            "x-position": 4
          },
          {
            "name": "JobState",
            "in": "query",
            "schema": {
              "$ref": "#/components/schemas/CloudBackupJobState"
            },
            "x-position": 5
          },
          {
            "name": "PageIndex",
            "in": "query",
            "schema": {
              "type": "integer",
              "format": "int32"
            },
            "x-position": 6
          },
          {
            "name": "PageSize",
            "in": "query",
            "schema": {
              "type": "integer",
              "format": "int32"
            },
            "x-position": 7
          }
        ],
        "responses": {
          "200": {
            "description": "",
            "content": {
              "application/json": {
                "schema": {
                  "$ref": "#/components/schemas/CloudBackupJobResult"
                }
              }
            }
          }
        }
      }
    }
  },
  "components": {
    "schemas": {
      "LicenseConsumption": {
        "allOf": [
          {
            "$ref": "#/components/schemas/PublicApiResponseBody"
          },
          {
            "type": "object",
            "additionalProperties": false,
            "properties": {
              "outOfPolicyTime": {
                "type": "integer",
                "format": "int64"
              },
              "purchasedUserSeats": {
                "type": "integer",
                "format": "int32"
              },
              "assignedUserSeats": {
                "type": "integer",
                "format": "int32"
              },
              "purchasedStorageSize": {
                "type": "integer",
                "format": "int32"
              },
              "protectedSize": {
                "type": "integer",
                "format": "int32"
              }
            }
          }
        ]
      },
      "PublicApiResponseBody": {
        "type": "object",
        "additionalProperties": false,
        "properties": {
          "traceId": {
            "type": "string",
            "nullable": true
          },
          "error": {
            "type": "string",
            "nullable": true
          }
        }
      },
      "PublicApiGetJobResult": {
        "allOf": [
          {
            "$ref": "#/components/schemas/PublicApiResponseBody"
          },
          {
            "type": "object",
            "additionalProperties": false,
            "properties": {
              "totalNumber": {
                "type": "integer",
                "format": "int32"
              },
              "jobs": {
                "type": "array",
                "nullable": true,
                "items": {
                  "$ref": "#/components/schemas/PublicApiGetJobInfo"
                }
              },
              "nextLink": {
                "type": "string",
                "nullable": true
              }
            }
          }
        ]
      },
      "PublicApiGetJobInfo": {
        "type": "object",
        "additionalProperties": false,
        "properties": {
          "id": {
            "type": "string",
            "nullable": true
          },
          "state": {
            "type": "string",
            "nullable": true
          },
          "startTime": {
            "type": "string",
            "nullable": true
          },
          "finishTime": {
            "type": "string",
            "nullable": true
          },
          "duration": {
            "type": "string",
            "nullable": true
          },
          "backupDetails": {
            "nullable": true,
            "oneOf": [
              {
                "$ref": "#/components/schemas/PublicApiBackupDetails"
              }
            ]
          },
          "jobErrors": {
            "type": "array",
            "nullable": true,
            "items": {
              "$ref": "#/components/schemas/ErrorCodeParam"
            }
          }
        }
      },
      "PublicApiBackupDetails": {
        "type": "object",
        "additionalProperties": false,
        "properties": {
          "totalNumber": {
            "type": "integer",
            "format": "int64"
          },
          "failedNumber": {
            "type": "integer",
            "format": "int64"
          },
          "successfulNumber": {
            "type": "integer",
            "format": "int64"
          },
          "skippedNumber": {
            "type": "integer",
            "format": "int64"
          }
        }
      },
      "ErrorCodeParam": {
        "type": "object",
        "additionalProperties": false,
        "properties": {
          "isErrorCode": {
            "type": "boolean"
          },
          "value": {
            "type": "string",
            "nullable": true
          },
          "url": {
            "type": "string",
            "nullable": true
          },
          "number": {
            "type": "integer",
            "format": "int32"
          }
        }
      },
      "BackupJobType": {
        "type": "integer",
        "description": "",
        "x-enumNames": [
          "All",
          "Backup",
          "Restore",
          "Export",
          "Delete",
          "Retention"
        ],
        "enum": [
          0,
          1,
          2,
          3,
          4,
          5
        ]
      },
      "CloudBackupJobObjectType": {
        "type": "integer",
        "description": "",
        "x-enumNames": [
          "All",
          "ExchangeOnline",
          "SharePointOnline",
          "OneDrive",
          "Groups",
          "ProjectOnline",
          "PublicFolder",
          "Teams",
          "YammerGroup",
          "PersonalChat",
          "PowerBI",
          "PowerAutomate",
          "PowerApps"
        ],
        "enum": [
          0,
          1,
          2,
          3,
          4,
          5,
          6,
          7,
          8,
          9,
          10,
          11,
          12
        ]
      },
      "CloudBackupJobState": {
        "type": "integer",
        "description": "",
        "x-enumNames": [
          "All",
          "InProgress",
          "Finished",
          "Failed",
          "FinishedException",
          "PartiallyFinished"
        ],
        "enum": [
          0,
          1,
          2,
          3,
          4,
          5
        ]
      },
      "PublicApiGetUnusualActivity": {
        "allOf": [
          {
            "$ref": "#/components/schemas/PublicApiResponseBody"
          },
          {
            "type": "object",
            "additionalProperties": false,
            "properties": {
              "data": {
                "type": "array",
                "nullable": true,
                "items": {
                  "$ref": "#/components/schemas/UnusualActivityData"
                }
              }
            }
          }
        ]
      },
      "UnusualActivityData": {
        "type": "object",
        "additionalProperties": false,
        "properties": {
          "tenantOwner": {
            "type": "string",
            "nullable": true
          },
          "tenantId": {
            "type": "string",
            "nullable": true
          },
          "serviceType": {
            "type": "integer",
            "format": "int32"
          },
          "potentialRansomwareAttackCount": {
            "type": "integer",
            "format": "int64"
          },
          "unusualActivitiesCount": {
            "type": "integer",
            "format": "int64"
          }
        }
      },
      "CloudBackupJobResult": {
        "allOf": [
          {
            "$ref": "#/components/schemas/PublicApiResponseBody"
          },
          {
            "type": "object",
            "additionalProperties": false,
            "properties": {
              "totalCount": {
                "type": "integer",
                "format": "int32"
              },
              "jobs": {
                "type": "array",
                "nullable": true,
                "items": {
                  "$ref": "#/components/schemas/CloudBackupJob"
                }
              },
              "nextLink": {
                "type": "string",
                "nullable": true
              }
            }
          }
        ]
      },
      "CloudBackupJob": {
        "type": "object",
        "additionalProperties": false,
        "properties": {
          "id": {
            "type": "string",
            "nullable": true
          },
          "state": {
            "type": "string",
            "nullable": true
          },
          "startTime": {
            "type": "integer",
            "format": "int64"
          },
          "finishTime": {
            "type": "integer",
            "format": "int64"
          },
          "duration": {
            "type": "integer",
            "format": "int64"
          },
          "backupDetails": {
            "nullable": true,
            "oneOf": [
              {
                "$ref": "#/components/schemas/BackupDetails"
              }
            ]
          },
          "jobErrors": {
            "type": "array",
            "nullable": true,
            "items": {
              "$ref": "#/components/schemas/ErrorCodeParam"
            }
          }
        }
      },
      "BackupDetails": {
        "type": "object",
        "additionalProperties": false,
        "properties": {
          "totalCount": {
            "type": "integer",
            "format": "int64"
          },
          "failedCount": {
            "type": "integer",
            "format": "int64"
          },
          "successfulCount": {
            "type": "integer",
            "format": "int64"
          },
          "skippedCount": {
            "type": "integer",
            "format": "int64"
          }
        }
      }
    },
    "securitySchemes": {
      "Bearer": {
        "type": "apiKey",
        "description": "Please enter into field the word 'Bearer' followed by a space and the JWT value",
        "name": "Authorization",
        "in": "header"
      }
    }
  }
}